gaip/README.md
gaip/VERSION
gaip/__init__.py
gaip/__main__.py
gaip/server.py
gaip/api/__init__.py
gaip/api/crud.py
gaip/db_model/__init__.py
gaip/db_model/models.py
gaip/factory/__init__.py
gaip/factory/database.py
gaip/user_schema/__init__.py
gaip/user_schema/schemas.py
gaip-0.0.1.dist-info/METADATA
gaip-0.0.1.dist-info/WHEEL
gaip-0.0.1.dist-info/entry_points.txt
gaip-0.0.1.dist-info/RECORD
